ShahMat/__init__.py
ShahMat/chesscom.py
shahmat-0.0.8.dist-info/METADATA
shahmat-0.0.8.dist-info/WHEEL
shahmat-0.0.8.dist-info/top_level.txt
shahmat-0.0.8.dist-info/RECORD
