Metadata-Version: 2.4
Name: shahmat
Version: 0.0.8
Summary: Analyze your Chess.com (Lichess in development) games: fetch, stats (hour, Elo diff), and clean visualizations.
Home-page: https://ag-algolab.github.io/
Author: Anthony Gocmen
Author-email: anthony.gocmen@gmail.com
License: MIT
Project-URL: Source, https://github.com/ag-algolab/ShahMat
Keywords: chess,chess.com,analytics,elo,visualization,data-science
Classifier: Programming Language :: Python :: 3
Classifier: Programming Language :: Python :: 3 :: Only
Classifier: Programming Language :: Python :: 3.9
Classifier: Programming Language :: Python :: 3.10
Classifier: Programming Language :: Python :: 3.11
Classifier: License :: OSI Approved :: MIT License
Classifier: Intended Audience :: Developers
Classifier: Intended Audience :: Science/Research
Classifier: Topic :: Games/Entertainment :: Board Games
Classifier: Topic :: Scientific/Engineering :: Information Analysis
Requires-Python: >=3.9
Requires-Dist: pandas>=1.3
Requires-Dist: numpy>=1.21
Requires-Dist: matplotlib>=3.5
Requires-Dist: tqdm>=4.64
Requires-Dist: requests>=2.28
Dynamic: author
Dynamic: author-email
Dynamic: classifier
Dynamic: description
Dynamic: description-content-type
Dynamic: home-page
Dynamic: keywords
Dynamic: license
Dynamic: project-url
Dynamic: requires-dist
Dynamic: requires-python
Dynamic: summary
